{"cameraMode":{"drawMode":0,"name":"Shaded","section":"Shading Mode"},"sceneLighting":true,"audioPlay":false,"sceneViewState":{"showFog":true,"showMaterialUpdate":false,"showSkybox":true,"showFlares":true,"showImageEffects":true,"showParticleSystems":true},"in2DMode":false,"pivot":{"x":0.7124365568161011,"y":-0.6641926169395447,"z":-0.47892940044403078},"rotation":{"x":-0.12036469578742981,"y":-0.06249895319342613,"z":0.007593323942273855,"w":-0.9907313585281372},"size":12.858707427978516,"orthographic":false}